{"name":"jpegcamsinatra","body":"###jpegcamsinatra\r\n\r\nWelcome!\r\n\r\nThis is a tiny Sinatra app that is designed to run on your local host and test Joseph Huckaby's **[jpegcam][1]** Javascript library.\r\n\r\n###Running\r\n\r\nClone this repo into a directory and start the app:\r\n\r\n    ruby app.rb\r\n\r\nThen browse this url:\r\n\r\n    http://localhost:4567/test.html\r\n\r\nEach time the ***Upload*** button is pressed, the image from the webcam will be written to a file named ***test.jpeg***.\r\n\r\n  [1]: http://code.google.com/p/jpegcam/\r\n\r\n\r\n","tagline":"A Sinatra server for Joseph Huckaby's jpegcam","google":"","note":"Don't delete this file! It's used internally to help with page regeneration."}